skimpy/__init__.py
skimpy/__main__.py
skimpy/py.typed
skimpy-0.0.20.dist-info/licenses/LICENSE
skimpy-0.0.20.dist-info/METADATA
skimpy-0.0.20.dist-info/WHEEL
skimpy-0.0.20.dist-info/entry_points.txt
skimpy-0.0.20.dist-info/top_level.txt
skimpy-0.0.20.dist-info/RECORD
