Metadata-Version: 2.4
Name: skimpy
Version: 0.0.20
Summary: skimpy
Author-email: Arthur Turrell <None@none.com>
License-Expression: MIT
Classifier: Development Status :: 5 - Production/Stable
Classifier: Programming Language :: Python :: 3.10
Classifier: Programming Language :: Python :: 3.11
Classifier: Programming Language :: Python :: 3.12
Classifier: Programming Language :: Python :: 3.13
Requires-Python: >=3.10
License-File: LICENSE
Requires-Dist: click>=8.1.7
Requires-Dist: ipykernel>=6.29.5
Requires-Dist: numpy>=2.0.2
Requires-Dist: pandas-stubs>=2.2.2.240807
Requires-Dist: pandas>=2.2.3
Requires-Dist: polars>=1.17.1
Requires-Dist: pygments>=2.18.0
Requires-Dist: rich>=13.9.4
Requires-Dist: typeguard>=4.4.1
Requires-Dist: pyarrow>=17.0.0
Requires-Dist: pydoclint>=0.6.0
Requires-Dist: duckdb>=1.2.2
Dynamic: license-file
